[
  {
    "sku": "B07MFR9MDR",
    "title": "Sponsored Ad - SME Bullseye Long Range Camera",
    "metaTitle": "Sponsored Ad - SME Bullseye Long Range Camera",
    "imageUrls": "https://m.media-amazon.com/images/I/61bMbO8vKAL._AC_UY218_.jpg",
    "status": "new",
    "price": 496.85,
    "discount": 2,
    "quantity": 29,
    "totalRatings": 120,
    "rateAverage": 4.3,
    "categoryId": "6278e4e919a7ab61193236f7",
    "atributeId": "",
    "descriptions": "Sponsored Ad - SME Bullseye Long Range Camera"
  },
  {
    "sku": "B07C2Z21X5",
    "title": "Canon EOS Rebel T7 DSLR Camera with 18-55mm Lens | Built-in Wi-Fi | 24.1 MP CMOS Sensor | DIGIC 4+ Image Processor and Ful...",
    "metaTitle": "Canon EOS Rebel T7 DSLR Camera with 18-55mm Lens | Built-in Wi-Fi | 24.1 MP CMOS Sensor | DIGIC 4+ Image Processor and Ful...",
    "imageUrls": "https://m.media-amazon.com/images/I/71EWRyqzw0L._AC_UY218_.jpg",
    "status": "new",
    "price": 233,
    "discount": 3,
    "quantity": 113,
    "totalRatings": 1948,
    "rateAverage": 4.7,
    "categoryId": "6278e4e919a7ab61193236f7",
    "atributeId": "",
    "descriptions": "Canon EOS Rebel T7 DSLR Camera with 18-55mm Lens | Built-in Wi-Fi | 24.1 MP CMOS Sensor | DIGIC 4+ Image Processor and Ful..."
  },
  {
    "sku": "B0779KBH92",
    "title": "Minolta 20 Mega Pixels Wifi Digital Camera with 35x Optical Zoom & 1080p HD Video Optical with 3-Inch LCD, 4.8 x 3.4 x 3....",
    "metaTitle": "Minolta 20 Mega Pixels Wifi Digital Camera with 35x Optical Zoom & 1080p HD Video Optical with 3-Inch LCD, 4.8 x 3.4 x 3....",
    "imageUrls": "https://m.media-amazon.com/images/I/71KEjwDRAiL._AC_UY218_.jpg",
    "status": "sale",
    "price": 249.99,
    "discount": 2,
    "quantity": 58,
    "totalRatings": 617,
    "rateAverage": 4.2,
    "categoryId": "6278e4e919a7ab61193236f7",
    "atributeId": "",
    "descriptions": "Minolta 20 Mega Pixels Wifi Digital Camera with 35x Optical Zoom & 1080p HD Video Optical with 3-Inch LCD, 4.8 x 3.4 x 3...."
  },
  {
    "sku": "B01MS16V42",
    "title": "Panasonic LUMIX FZ80 4K Digital Camera, 18.1 Megapixel Video Camera, 60X Zoom DC VARIO 20-1200mm Lens, F2.8-5.9 Aperture, ...",
    "metaTitle": "Panasonic LUMIX FZ80 4K Digital Camera, 18.1 Megapixel Video Camera, 60X Zoom DC VARIO 20-1200mm Lens, F2.8-5.9 Aperture, ...",
    "imageUrls": "https://m.media-amazon.com/images/I/917LEZ+it3L._AC_UY218_.jpg",
    "status": "new",
    "price": 297.99,
    "discount": 2,
    "quantity": 77,
    "totalRatings": 2687,
    "rateAverage": 4.5,
    "categoryId": "6278e4e919a7ab61193236f7",
    "atributeId": "",
    "descriptions": "Panasonic LUMIX FZ80 4K Digital Camera, 18.1 Megapixel Video Camera, 60X Zoom DC VARIO 20-1200mm Lens, F2.8-5.9 Aperture, ..."
  },
  {
    "sku": "B07S7VBGLJ",
    "title": "Minolta Pro Shot 20 Mega Pixel HD Digital Camera with 67X Optical Zoom, Full 1080P HD Video & 16GB SD Card, Black",
    "metaTitle": "Minolta Pro Shot 20 Mega Pixel HD Digital Camera with 67X Optical Zoom, Full 1080P HD Video & 16GB SD Card, Black",
    "imageUrls": "https://m.media-amazon.com/images/I/71zbWtYBZhL._AC_UY218_.jpg",
    "status": "new",
    "price": 399,
    "discount": 8,
    "quantity": 84,
    "totalRatings": 202,
    "rateAverage": 4.3,
    "categoryId": "6278e4e919a7ab61193236f7",
    "atributeId": "",
    "descriptions": "Minolta Pro Shot 20 Mega Pixel HD Digital Camera with 67X Optical Zoom, Full 1080P HD Video & 16GB SD Card, Black"
  },
  {
    "sku": "B011PKJI2Y",
    "title": "Panasonic LUMIX FZ300 Long Zoom Digital Camera Features 12.1 Megapixel, 1/2.3-Inch Sensor, 4K Video, WiFi, Splash & Dustpr...",
    "metaTitle": "Panasonic LUMIX FZ300 Long Zoom Digital Camera Features 12.1 Megapixel, 1/2.3-Inch Sensor, 4K Video, WiFi, Splash & Dustpr...",
    "imageUrls": "https://m.media-amazon.com/images/I/81xVbbwlqlL._AC_UY218_.jpg",
    "status": "new",
    "price": 447.99,
    "discount": 4,
    "quantity": 107,
    "totalRatings": 2048,
    "rateAverage": 4.6,
    "categoryId": "6278e4e919a7ab61193236f7",
    "atributeId": "",
    "descriptions": "Panasonic LUMIX FZ300 Long Zoom Digital Camera Features 12.1 Megapixel, 1/2.3-Inch Sensor, 4K Video, WiFi, Splash & Dustpr..."
  },
  {
    "sku": "B09NP4SXL9",
    "title": "Minolta Pro Shot 16 Mega Pixel HD Digital Camera with 53x Optical Zoom, Full 1080p HD Video & 16GB SD Card, MN53Z, Red",
    "metaTitle": "Minolta Pro Shot 16 Mega Pixel HD Digital Camera with 53x Optical Zoom, Full 1080p HD Video & 16GB SD Card, MN53Z, Red",
    "imageUrls": "https://m.media-amazon.com/images/I/611My491m5L._AC_UY218_.jpg",
    "status": "sale",
    "price": 269,
    "discount": 2,
    "quantity": 116,
    "totalRatings": 3,
    "rateAverage": 4.6,
    "categoryId": "6278e4e919a7ab61193236f7",
    "atributeId": "",
    "descriptions": "Minolta Pro Shot 16 Mega Pixel HD Digital Camera with 53x Optical Zoom, Full 1080p HD Video & 16GB SD Card, MN53Z, Red"
  },
  {
    "sku": "B098GZR4D5",
    "title": "Sponsored Ad - Minolta 48 MP Dual Screen Waterproof Digital Camera MN40WP",
    "metaTitle": "Sponsored Ad - Minolta 48 MP Dual Screen Waterproof Digital Camera MN40WP",
    "imageUrls": "https://m.media-amazon.com/images/I/71ezSbCylyS._AC_UY218_.jpg",
    "status": "sale",
    "price": 101.99,
    "discount": 8,
    "quantity": 75,
    "totalRatings": 15,
    "rateAverage": 3.9,
    "categoryId": "6278e4e919a7ab61193236f7",
    "atributeId": "",
    "descriptions": "Sponsored Ad - Minolta 48 MP Dual Screen Waterproof Digital Camera MN40WP"
  },
  {
    "sku": "B07MFR9MDR",
    "title": "Sponsored Ad - SME Bullseye Long Range Camera",
    "metaTitle": "Sponsored Ad - SME Bullseye Long Range Camera",
    "imageUrls": "https://m.media-amazon.com/images/I/61bMbO8vKAL._AC_UY218_.jpg",
    "status": "new",
    "price": 496.85,
    "discount": 11,
    "quantity": 103,
    "totalRatings": 120,
    "rateAverage": 4.3,
    "categoryId": "6278e4e919a7ab61193236f7",
    "atributeId": "",
    "descriptions": "Sponsored Ad - SME Bullseye Long Range Camera"
  },
  {
    "sku": "B08N5LKJLV",
    "title": "OLYMPUS OM-D E-M10 Mark IIIs Black Body with Black M.Zuiko Digital 14-42mm F3.5-5.6 IIR Lens, V207111BU000",
    "metaTitle": "OLYMPUS OM-D E-M10 Mark IIIs Black Body with Black M.Zuiko Digital 14-42mm F3.5-5.6 IIR Lens, V207111BU000",
    "imageUrls": "https://m.media-amazon.com/images/I/61lGUzxb5JL._AC_UY218_.jpg",
    "status": "sale",
    "price": 599,
    "discount": 4,
    "quantity": 113,
    "totalRatings": 109,
    "rateAverage": 4.8,
    "categoryId": "6278e4e919a7ab61193236f7",
    "atributeId": "",
    "descriptions": "OLYMPUS OM-D E-M10 Mark IIIs Black Body with Black M.Zuiko Digital 14-42mm F3.5-5.6 IIR Lens, V207111BU000"
  },
  {
    "sku": "B085NX5JTN",
    "title": "OLYMPUS OM-D E-M5 Mark III Black Body with Black M.Zuiko Digital ED 12-45mm F4.0 PRO Lens Kit",
    "metaTitle": "OLYMPUS OM-D E-M5 Mark III Black Body with Black M.Zuiko Digital ED 12-45mm F4.0 PRO Lens Kit",
    "imageUrls": "https://m.media-amazon.com/images/I/81D1i4xJc9L._AC_UY218_.jpg",
    "status": "new",
    "price": 1299.99,
    "discount": 8,
    "quantity": 120,
    "totalRatings": 208,
    "rateAverage": 4.7,
    "categoryId": "6278e4e919a7ab61193236f7",
    "atributeId": "",
    "descriptions": "OLYMPUS OM-D E-M5 Mark III Black Body with Black M.Zuiko Digital ED 12-45mm F4.0 PRO Lens Kit"
  },
  {
    "sku": "B08BTTMQQH",
    "title": "Canon EOS 2000D (Rebel T7) DSLR Camera with EF-S 18-55mm f/3.5-5.6 DC III Lens - Ultimate Accessory Bundle Includes: 2X Sa...",
    "metaTitle": "Canon EOS 2000D (Rebel T7) DSLR Camera with EF-S 18-55mm f/3.5-5.6 DC III Lens - Ultimate Accessory Bundle Includes: 2X Sa...",
    "imageUrls": "https://m.media-amazon.com/images/I/81tsOg+mKlL._AC_UY218_.jpg",
    "status": "new",
    "price": 539,
    "discount": 6,
    "quantity": 51,
    "totalRatings": 193,
    "rateAverage": 4.5,
    "categoryId": "6278e4e919a7ab61193236f7",
    "atributeId": "",
    "descriptions": "Canon EOS 2000D (Rebel T7) DSLR Camera with EF-S 18-55mm f/3.5-5.6 DC III Lens - Ultimate Accessory Bundle Includes: 2X Sa..."
  },
  {
    "sku": "B071K62DPM",
    "title": "Canon EOS 6D Mark II with EF 24-105mm IS STM Lens, WiFi Enabled",
    "metaTitle": "Canon EOS 6D Mark II with EF 24-105mm IS STM Lens, WiFi Enabled",
    "imageUrls": "https://m.media-amazon.com/images/I/71O5SzidzRL._AC_UY218_.jpg",
    "status": "new",
    "price": 2399,
    "discount": 9,
    "quantity": 21,
    "totalRatings": 994,
    "rateAverage": 4.8,
    "categoryId": "6278e4e919a7ab61193236f7",
    "atributeId": "",
    "descriptions": "Canon EOS 6D Mark II with EF 24-105mm IS STM Lens, WiFi Enabled"
  },
  {
    "sku": "B07DCZRPYV",
    "title": "Kodak PIXPRO Astro Zoom AZ252-RD 16MP Digital Camera with 25X Optical Zoom and 3\" LCD (Red)",
    "metaTitle": "Kodak PIXPRO Astro Zoom AZ252-RD 16MP Digital Camera with 25X Optical Zoom and 3\" LCD (Red)",
    "imageUrls": "https://m.media-amazon.com/images/I/81hsyfdjRpS._AC_UY218_.jpg",
    "status": "new",
    "price": 164.95,
    "discount": 6,
    "quantity": 102,
    "totalRatings": 1599,
    "rateAverage": 4.3,
    "categoryId": "6278e4e919a7ab61193236f7",
    "atributeId": "",
    "descriptions": "Kodak PIXPRO Astro Zoom AZ252-RD 16MP Digital Camera with 25X Optical Zoom and 3\" LCD (Red)"
  },
  {
    "sku": "B098GZR4D5",
    "title": "Sponsored Ad - Minolta 48 MP Dual Screen Waterproof Digital Camera MN40WP",
    "metaTitle": "Sponsored Ad - Minolta 48 MP Dual Screen Waterproof Digital Camera MN40WP",
    "imageUrls": "https://m.media-amazon.com/images/I/71ezSbCylyS._AC_UY218_.jpg",
    "status": "new",
    "price": 101.99,
    "discount": 11,
    "quantity": 23,
    "totalRatings": 15,
    "rateAverage": 3.9,
    "categoryId": "6278e4e919a7ab61193236f7",
    "atributeId": "",
    "descriptions": "Sponsored Ad - Minolta 48 MP Dual Screen Waterproof Digital Camera MN40WP"
  },
  {
    "sku": "B0007UQNKY",
    "title": "Sponsored Ad - Celestron - PowerSeeker 127EQ Telescope - Manual German Equatorial Telescope for Beginners - Compact and Po...",
    "metaTitle": "Sponsored Ad - Celestron - PowerSeeker 127EQ Telescope - Manual German Equatorial Telescope for Beginners - Compact and Po...",
    "imageUrls": "https://m.media-amazon.com/images/I/61Squ7U2zRL._AC_UY218_.jpg",
    "status": "new",
    "price": 179.95,
    "discount": 4,
    "quantity": 116,
    "totalRatings": 6856,
    "rateAverage": 4.2,
    "categoryId": "6278e4e919a7ab61193236f7",
    "atributeId": "",
    "descriptions": "Sponsored Ad - Celestron - PowerSeeker 127EQ Telescope - Manual German Equatorial Telescope for Beginners - Compact and Po..."
  },
  {
    "sku": "B09LZCPS6C",
    "title": "Canon EOS 2000D with EFS 1855mm III Lens with Starter Accessory Bundle Includes SanDisk Ultra 64GB SDXC, Dig CN2000D1855II...",
    "metaTitle": "Canon EOS 2000D with EFS 1855mm III Lens with Starter Accessory Bundle Includes SanDisk Ultra 64GB SDXC, Dig CN2000D1855II...",
    "imageUrls": "https://m.media-amazon.com/images/I/81wFHT8creL._AC_UY218_.jpg",
    "status": "sale",
    "price": 499.95,
    "discount": 5,
    "quantity": 114,
    "totalRatings": 1,
    "rateAverage": 5,
    "categoryId": "6278e4e919a7ab61193236f7",
    "atributeId": "",
    "descriptions": "Canon EOS 2000D with EFS 1855mm III Lens with Starter Accessory Bundle Includes SanDisk Ultra 64GB SDXC, Dig CN2000D1855II..."
  },
  {
    "sku": "B00X409O6O",
    "title": "Panasonic LUMIX G7KS 4K Mirrorless Camera, 16 Megapixel Digital Camera, 14-42 mm Lens Kit, DMC-G7KS",
    "metaTitle": "Panasonic LUMIX G7KS 4K Mirrorless Camera, 16 Megapixel Digital Camera, 14-42 mm Lens Kit, DMC-G7KS",
    "imageUrls": "https://m.media-amazon.com/images/I/81sdQzBKNFL._AC_UY218_.jpg",
    "status": "new",
    "price": 597.99,
    "discount": 7,
    "quantity": 30,
    "totalRatings": 1525,
    "rateAverage": 4.7,
    "categoryId": "6278e4e919a7ab61193236f7",
    "atributeId": "",
    "descriptions": "Panasonic LUMIX G7KS 4K Mirrorless Camera, 16 Megapixel Digital Camera, 14-42 mm Lens Kit, DMC-G7KS"
  },
  {
    "sku": "B07GWKDLGT",
    "title": "Nikon D3500 W/ AF-P DX NIKKOR 18-55mm f/3.5-5.6G VR Black",
    "metaTitle": "Nikon D3500 W/ AF-P DX NIKKOR 18-55mm f/3.5-5.6G VR Black",
    "imageUrls": "https://m.media-amazon.com/images/I/71TSinb4usL._AC_UY218_.jpg",
    "status": "new",
    "price": 696.95,
    "discount": 11,
    "quantity": 118,
    "totalRatings": 3397,
    "rateAverage": 4.8,
    "categoryId": "6278e4e919a7ab61193236f7",
    "atributeId": "",
    "descriptions": "Nikon D3500 W/ AF-P DX NIKKOR 18-55mm f/3.5-5.6G VR Black"
  },
  {
    "sku": "B00I8BIC9E",
    "title": "Sony (DSCW800) 20.1 MP Digital Camera (Silver)",
    "metaTitle": "Sony (DSCW800) 20.1 MP Digital Camera (Silver)",
    "imageUrls": "https://m.media-amazon.com/images/I/61fIEs7CAuL._AC_UY218_.jpg",
    "status": "new",
    "price": 469,
    "discount": 4,
    "quantity": 21,
    "totalRatings": 1242,
    "rateAverage": 4.1,
    "categoryId": "6278e4e919a7ab61193236f7",
    "atributeId": "",
    "descriptions": "Sony (DSCW800) 20.1 MP Digital Camera (Silver)"
  },
  {
    "sku": "B0868VXPCK",
    "title": "Panasonic Lumix DC-FZ80 4K Digital Camera, 18.1 Megapixel, 60x Zoom 20-1200mm Lens Bundle with Bag, 32GB SD Card, Corel PC...",
    "metaTitle": "Panasonic Lumix DC-FZ80 4K Digital Camera, 18.1 Megapixel, 60x Zoom 20-1200mm Lens Bundle with Bag, 32GB SD Card, Corel PC...",
    "imageUrls": "https://m.media-amazon.com/images/I/81CUtRHdksL._AC_UY218_.jpg",
    "status": "sale",
    "price": 329.99,
    "discount": 9,
    "quantity": 55,
    "totalRatings": 86,
    "rateAverage": 4.5,
    "categoryId": "6278e4e919a7ab61193236f7",
    "atributeId": "",
    "descriptions": "Panasonic Lumix DC-FZ80 4K Digital Camera, 18.1 Megapixel, 60x Zoom 20-1200mm Lens Bundle with Bag, 32GB SD Card, Corel PC..."
  },
  {
    "sku": "B072XL3LGC",
    "title": "Sponsored Ad - SIRUI 59'' Tripod for Camera, 2-in-1 Aluminum Camera Tripod Monopod, Compact Travel Tripod with 360°Panoram...",
    "metaTitle": "Sponsored Ad - SIRUI 59'' Tripod for Camera, 2-in-1 Aluminum Camera Tripod Monopod, Compact Travel Tripod with 360°Panoram...",
    "imageUrls": "https://m.media-amazon.com/images/I/514v+8DsyEL._AC_UY218_.jpg",
    "status": "sale",
    "price": 149.99,
    "discount": 5,
    "quantity": 65,
    "totalRatings": 209,
    "rateAverage": 4.6,
    "categoryId": "6278e4e919a7ab61193236f7",
    "atributeId": "",
    "descriptions": "Sponsored Ad - SIRUI 59'' Tripod for Camera, 2-in-1 Aluminum Camera Tripod Monopod, Compact Travel Tripod with 360°Panoram..."
  },
  {
    "sku": "B07ZBP9727",
    "title": "Canon PowerShot ELPH 180 Digital Camera + 64 GB Memory Card (Silver)",
    "metaTitle": "Canon PowerShot ELPH 180 Digital Camera + 64 GB Memory Card (Silver)",
    "imageUrls": "https://m.media-amazon.com/images/I/71qyMD7PU9L._AC_UY218_.jpg",
    "status": "sale",
    "price": 399.95,
    "discount": 5,
    "quantity": 47,
    "totalRatings": 28,
    "rateAverage": 4.3,
    "categoryId": "6278e4e919a7ab61193236f7",
    "atributeId": "",
    "descriptions": "Canon PowerShot ELPH 180 Digital Camera + 64 GB Memory Card (Silver)"
  },
  {
    "sku": "B0868VMW7G",
    "title": "Panasonic Lumix DC-FZ80 4K Digital Camera, 18.1 Megapixel, 60x Zoom 20-1200mm Lens Essential Bundle with Peak Design Wrist...",
    "metaTitle": "Panasonic Lumix DC-FZ80 4K Digital Camera, 18.1 Megapixel, 60x Zoom 20-1200mm Lens Essential Bundle with Peak Design Wrist...",
    "imageUrls": "https://m.media-amazon.com/images/I/81uPnY++cUL._AC_UY218_.jpg",
    "status": "sale",
    "price": 339.99,
    "discount": 6,
    "quantity": 88,
    "totalRatings": 18,
    "rateAverage": 4.9,
    "categoryId": "6278e4e919a7ab61193236f7",
    "atributeId": "",
    "descriptions": "Panasonic Lumix DC-FZ80 4K Digital Camera, 18.1 Megapixel, 60x Zoom 20-1200mm Lens Essential Bundle with Peak Design Wrist..."
  },
  {
    "sku": "B07NPDB2ZZ",
    "title": "Minolta M35Z 20MP 1080p HD Bridge Digital Camera with 35x Optical Zoom, RED - Bundle with Camera Case, 16GB SDHC Card, Mem...",
    "metaTitle": "Minolta M35Z 20MP 1080p HD Bridge Digital Camera with 35x Optical Zoom, RED - Bundle with Camera Case, 16GB SDHC Card, Mem...",
    "imageUrls": "https://m.media-amazon.com/images/I/61aNvClbsOL._AC_UY218_.jpg",
    "status": "new",
    "price": 249,
    "discount": 7,
    "quantity": 82,
    "totalRatings": 19,
    "rateAverage": 4.3,
    "categoryId": "6278e4e919a7ab61193236f7",
    "atributeId": "",
    "descriptions": "Minolta M35Z 20MP 1080p HD Bridge Digital Camera with 35x Optical Zoom, RED - Bundle with Camera Case, 16GB SDHC Card, Mem..."
  },
  {
    "sku": "B07NP148XX",
    "title": "Minolta M35Z 20MP 1080p HD Bridge Digital Camera with 35x Optical Zoom, Purple - Bundle with Camera Case, 16GB SDHC Card, ...",
    "metaTitle": "Minolta M35Z 20MP 1080p HD Bridge Digital Camera with 35x Optical Zoom, Purple - Bundle with Camera Case, 16GB SDHC Card, ...",
    "imageUrls": "https://m.media-amazon.com/images/I/61pcjVjGtBL._AC_UY218_.jpg",
    "status": "sale",
    "price": 235,
    "discount": 11,
    "quantity": 95,
    "totalRatings": 99,
    "rateAverage": 4.3,
    "categoryId": "6278e4e919a7ab61193236f7",
    "atributeId": "",
    "descriptions": "Minolta M35Z 20MP 1080p HD Bridge Digital Camera with 35x Optical Zoom, Purple - Bundle with Camera Case, 16GB SDHC Card, ..."
  },
  {
    "sku": "B079VDF7ZG",
    "title": "Panasonic LUMIX GX85 4K Digital Camera, 12-32mm and 45-150mm Lens Bundle, 16 Megapixel Mirrorless Camera Kit, 5 Axis In-Bo...",
    "metaTitle": "Panasonic LUMIX GX85 4K Digital Camera, 12-32mm and 45-150mm Lens Bundle, 16 Megapixel Mirrorless Camera Kit, 5 Axis In-Bo...",
    "imageUrls": "https://m.media-amazon.com/images/I/81BCS8w0v9L._AC_UY218_.jpg",
    "status": "sale",
    "price": 597.99,
    "discount": 10,
    "quantity": 41,
    "totalRatings": 699,
    "rateAverage": 4.7,
    "categoryId": "6278e4e919a7ab61193236f7",
    "atributeId": "",
    "descriptions": "Panasonic LUMIX GX85 4K Digital Camera, 12-32mm and 45-150mm Lens Bundle, 16 Megapixel Mirrorless Camera Kit, 5 Axis In-Bo..."
  },
  {
    "sku": "B07WHV3HXL",
    "title": "Canon DSLR Camera [EOS 90D] with 18-135 is USM Lens | Built-in Wi-Fi, Bluetooth, DIGIC 8 Image Processor, 4K Video, Dual P...",
    "metaTitle": "Canon DSLR Camera [EOS 90D] with 18-135 is USM Lens | Built-in Wi-Fi, Bluetooth, DIGIC 8 Image Processor, 4K Video, Dual P...",
    "imageUrls": "https://m.media-amazon.com/images/I/61f9Hy-cujL._AC_UY218_.jpg",
    "status": "new",
    "price": 389,
    "discount": 8,
    "quantity": 102,
    "totalRatings": 451,
    "rateAverage": 4.7,
    "categoryId": "6278e4e919a7ab61193236f7",
    "atributeId": "",
    "descriptions": "Canon DSLR Camera [EOS 90D] with 18-135 is USM Lens | Built-in Wi-Fi, Bluetooth, DIGIC 8 Image Processor, 4K Video, Dual P..."
  },
  {
    "sku": "B01KITZKDE",
    "title": "Nikon D3400 w/ AF-P DX NIKKOR 18-55mm f/3.5-5.6G VR (Black)",
    "metaTitle": "Nikon D3400 w/ AF-P DX NIKKOR 18-55mm f/3.5-5.6G VR (Black)",
    "imageUrls": "https://m.media-amazon.com/images/I/71pbiTKTCnL._AC_UY218_.jpg",
    "status": "sale",
    "price": 305,
    "discount": 9,
    "quantity": 119,
    "totalRatings": 2698,
    "rateAverage": 4.7,
    "categoryId": "6278e4e919a7ab61193236f7",
    "atributeId": "",
    "descriptions": "Nikon D3400 w/ AF-P DX NIKKOR 18-55mm f/3.5-5.6G VR (Black)"
  },
  {
    "sku": "B098GZR4D5",
    "title": "Sponsored Ad - Minolta 48 MP Dual Screen Waterproof Digital Camera MN40WP",
    "metaTitle": "Sponsored Ad - Minolta 48 MP Dual Screen Waterproof Digital Camera MN40WP",
    "imageUrls": "https://m.media-amazon.com/images/I/71ezSbCylyS._AC_UY218_.jpg",
    "status": "new",
    "price": 101.99,
    "discount": 9,
    "quantity": 66,
    "totalRatings": 15,
    "rateAverage": 3.9,
    "categoryId": "6278e4e919a7ab61193236f7",
    "atributeId": "",
    "descriptions": "Sponsored Ad - Minolta 48 MP Dual Screen Waterproof Digital Camera MN40WP"
  },
  {
    "sku": "B08WHWC688",
    "title": "Canon EOS Rebel T100/4000D DSLR Camera with 18-55mm f/3.5-5.6 Zoom Lens and Advanced Accessory Bundle: Bundle Includes - S...",
    "metaTitle": "Canon EOS Rebel T100/4000D DSLR Camera with 18-55mm f/3.5-5.6 Zoom Lens and Advanced Accessory Bundle: Bundle Includes - S...",
    "imageUrls": "https://m.media-amazon.com/images/I/81iFA1fw4FL._AC_UY218_.jpg",
    "status": "new",
    "price": 479.95,
    "discount": 9,
    "quantity": 113,
    "totalRatings": 81,
    "rateAverage": 4.6,
    "categoryId": "6278e4e919a7ab61193236f7",
    "atributeId": "",
    "descriptions": "Canon EOS Rebel T100/4000D DSLR Camera with 18-55mm f/3.5-5.6 Zoom Lens and Advanced Accessory Bundle: Bundle Includes - S..."
  },
  {
    "sku": "B08BG597S8",
    "title": "Panasonic LUMIX G100 4k Mirrorless Camera, Lightweight Camera for Photo and Video, Built-in Microphone, Micro Four Thirds ...",
    "metaTitle": "Panasonic LUMIX G100 4k Mirrorless Camera, Lightweight Camera for Photo and Video, Built-in Microphone, Micro Four Thirds ...",
    "imageUrls": "https://m.media-amazon.com/images/I/81kX+tkFboL._AC_UY218_.jpg",
    "status": "sale",
    "price": 799.99,
    "discount": 5,
    "quantity": 49,
    "totalRatings": 45,
    "rateAverage": 4.5,
    "categoryId": "6278e4e919a7ab61193236f7",
    "atributeId": "",
    "descriptions": "Panasonic LUMIX G100 4k Mirrorless Camera, Lightweight Camera for Photo and Video, Built-in Microphone, Micro Four Thirds ..."
  },
  {
    "sku": "B01M050N05",
    "title": "Panasonic LUMIX G85 4K Digital Camera, 12-60mm Power O.I.S. Lens, 16 Megapixel Mirrorless Camera, 5 Axis In-Body Dual Imag...",
    "metaTitle": "Panasonic LUMIX G85 4K Digital Camera, 12-60mm Power O.I.S. Lens, 16 Megapixel Mirrorless Camera, 5 Axis In-Body Dual Imag...",
    "imageUrls": "https://m.media-amazon.com/images/I/81TUnaSLzoL._AC_UY218_.jpg",
    "status": "new",
    "price": 699.99,
    "discount": 8,
    "quantity": 100,
    "totalRatings": 553,
    "rateAverage": 4.7,
    "categoryId": "6278e4e919a7ab61193236f7",
    "atributeId": "",
    "descriptions": "Panasonic LUMIX G85 4K Digital Camera, 12-60mm Power O.I.S. Lens, 16 Megapixel Mirrorless Camera, 5 Axis In-Body Dual Imag..."
  },
  {
    "sku": "B012T29V06",
    "title": "KODAK 16 Friendly Zoom Fz152 with 3\" LCD, Black (FZ152-BK)",
    "metaTitle": "KODAK 16 Friendly Zoom Fz152 with 3\" LCD, Black (FZ152-BK)",
    "imageUrls": "https://m.media-amazon.com/images/I/71EzZHveM-L._AC_UY218_.jpg",
    "status": "sale",
    "price": 129.99,
    "discount": 2,
    "quantity": 92,
    "totalRatings": 915,
    "rateAverage": 4,
    "categoryId": "6278e4e919a7ab61193236f7",
    "atributeId": "",
    "descriptions": "KODAK 16 Friendly Zoom Fz152 with 3\" LCD, Black (FZ152-BK)"
  },
  {
    "sku": "B0007UQNKY",
    "title": "Sponsored Ad - Celestron - PowerSeeker 127EQ Telescope - Manual German Equatorial Telescope for Beginners - Compact and Po...",
    "metaTitle": "Sponsored Ad - Celestron - PowerSeeker 127EQ Telescope - Manual German Equatorial Telescope for Beginners - Compact and Po...",
    "imageUrls": "https://m.media-amazon.com/images/I/61Squ7U2zRL._AC_UY218_.jpg",
    "status": "new",
    "price": 179.95,
    "discount": 4,
    "quantity": 90,
    "totalRatings": 6856,
    "rateAverage": 4.2,
    "categoryId": "6278e4e919a7ab61193236f7",
    "atributeId": "",
    "descriptions": "Sponsored Ad - Celestron - PowerSeeker 127EQ Telescope - Manual German Equatorial Telescope for Beginners - Compact and Po..."
  },
  {
    "sku": "B06Y5RTN1T",
    "title": "Nikon D7500 20.9MP DSLR Camera with AF-S DX NIKKOR 18-140mm f/3.5-5.6G ED VR Lens, Black",
    "metaTitle": "Nikon D7500 20.9MP DSLR Camera with AF-S DX NIKKOR 18-140mm f/3.5-5.6G ED VR Lens, Black",
    "imageUrls": "https://m.media-amazon.com/images/I/613pf1JTs9L._AC_UY218_.jpg",
    "status": "sale",
    "price": 468,
    "discount": 6,
    "quantity": 93,
    "totalRatings": 984,
    "rateAverage": 4.8,
    "categoryId": "6278e4e919a7ab61193236f7",
    "atributeId": "",
    "descriptions": "Nikon D7500 20.9MP DSLR Camera with AF-S DX NIKKOR 18-140mm f/3.5-5.6G ED VR Lens, Black"
  },
  {
    "sku": "B07RRD8P9F",
    "title": "Canon International EOS 4000D DSLR Camera with EF-S 18-55mm f/3.5-5.6 III Lens & Deluxe Accessory Bundle - Includes: SanDi...",
    "metaTitle": "Canon International EOS 4000D DSLR Camera with EF-S 18-55mm f/3.5-5.6 III Lens & Deluxe Accessory Bundle - Includes: SanDi...",
    "imageUrls": "https://m.media-amazon.com/images/I/81G990r2PLL._AC_UY218_.jpg",
    "status": "sale",
    "price": 479.95,
    "discount": 4,
    "quantity": 68,
    "totalRatings": 44,
    "rateAverage": 4.5,
    "categoryId": "6278e4e919a7ab61193236f7",
    "atributeId": "",
    "descriptions": "Canon International EOS 4000D DSLR Camera with EF-S 18-55mm f/3.5-5.6 III Lens & Deluxe Accessory Bundle - Includes: SanDi..."
  },
  {
    "sku": "B07RC8HPHL",
    "title": "OLYMPUS Tough TG-6 Waterproof Camera, Red",
    "metaTitle": "OLYMPUS Tough TG-6 Waterproof Camera, Red",
    "imageUrls": "https://m.media-amazon.com/images/I/61J18Xn9bfS._AC_UY218_.jpg",
    "status": "sale",
    "price": 449,
    "discount": 9,
    "quantity": 113,
    "totalRatings": 1640,
    "rateAverage": 4.5,
    "categoryId": "6278e4e919a7ab61193236f7",
    "atributeId": "",
    "descriptions": "OLYMPUS Tough TG-6 Waterproof Camera, Red"
  },
  {
    "sku": "B01LX7JSPJ",
    "title": "Panasonic LUMIX FZ2500 4K Point and Shoot Camera, 20X LEICA DC VARIO-ELMARIT F2.8-4.5 Lens, 21.1 Megapixels, 1 Inch High S...",
    "metaTitle": "Panasonic LUMIX FZ2500 4K Point and Shoot Camera, 20X LEICA DC VARIO-ELMARIT F2.8-4.5 Lens, 21.1 Megapixels, 1 Inch High S...",
    "imageUrls": "https://m.media-amazon.com/images/I/81A3oMbPGsL._AC_UY218_.jpg",
    "status": "new",
    "price": 897.99,
    "discount": 9,
    "quantity": 32,
    "totalRatings": 105,
    "rateAverage": 4.3,
    "categoryId": "6278e4e919a7ab61193236f7",
    "atributeId": "",
    "descriptions": "Panasonic LUMIX FZ2500 4K Point and Shoot Camera, 20X LEICA DC VARIO-ELMARIT F2.8-4.5 Lens, 21.1 Megapixels, 1 Inch High S..."
  },
  {
    "sku": "B07MC572D3",
    "title": "Sponsored Ad - SME WiFi Spotting Scope Camera",
    "metaTitle": "Sponsored Ad - SME WiFi Spotting Scope Camera",
    "imageUrls": "https://m.media-amazon.com/images/I/515YqPGPV3L._AC_UY218_.jpg",
    "status": "new",
    "price": 81.43,
    "discount": 5,
    "quantity": 114,
    "totalRatings": 371,
    "rateAverage": 3.9,
    "categoryId": "6278e4e919a7ab61193236f7",
    "atributeId": "",
    "descriptions": "Sponsored Ad - SME WiFi Spotting Scope Camera"
  },
  {
    "sku": "B081ZXPJL1",
    "title": "Sponsored Ad - UBeesize 10’’ LED Ring Light with Stand and Phone Holder, Selfie Halo Light for Photography/Makeup/Vloggin...",
    "metaTitle": "Sponsored Ad - UBeesize 10’’ LED Ring Light with Stand and Phone Holder, Selfie Halo Light for Photography/Makeup/Vloggin...",
    "imageUrls": "https://m.media-amazon.com/images/I/61x7Mlnf3xL._AC_UY218_.jpg",
    "status": "sale",
    "price": 35.99,
    "discount": 10,
    "quantity": 114,
    "totalRatings": 14290,
    "rateAverage": 4.5,
    "categoryId": "6278e4e919a7ab61193236f7",
    "atributeId": "",
    "descriptions": "Sponsored Ad - UBeesize 10’’ LED Ring Light with Stand and Phone Holder, Selfie Halo Light for Photography/Makeup/Vloggin..."
  },
  {
    "sku": "B072XL3LGC",
    "title": "Sponsored Ad - SIRUI 59'' Tripod for Camera, 2-in-1 Aluminum Camera Tripod Monopod, Compact Travel Tripod with 360°Panoram...",
    "metaTitle": "Sponsored Ad - SIRUI 59'' Tripod for Camera, 2-in-1 Aluminum Camera Tripod Monopod, Compact Travel Tripod with 360°Panoram...",
    "imageUrls": "https://m.media-amazon.com/images/I/514v+8DsyEL._AC_UY218_.jpg",
    "status": "sale",
    "price": 149.99,
    "discount": 2,
    "quantity": 104,
    "totalRatings": 209,
    "rateAverage": 4.6,
    "categoryId": "6278e4e919a7ab61193236f7",
    "atributeId": "",
    "descriptions": "Sponsored Ad - SIRUI 59'' Tripod for Camera, 2-in-1 Aluminum Camera Tripod Monopod, Compact Travel Tripod with 360°Panoram..."
  },
  {
    "sku": "B0868W1QDQ",
    "title": "Canon EOS 4000D DSLR Camera with EF-S 18-55mm f/3.5-5.6 III Lens & 500mm Preset Lens Beginner’s Bundle - Includes: SanDisk...",
    "metaTitle": "Canon EOS 4000D DSLR Camera with EF-S 18-55mm f/3.5-5.6 III Lens & 500mm Preset Lens Beginner’s Bundle - Includes: SanDisk...",
    "imageUrls": "https://m.media-amazon.com/images/I/81sSdpUaQVL._AC_UY218_.jpg",
    "status": "new",
    "price": 499.95,
    "discount": 8,
    "quantity": 65,
    "totalRatings": 46,
    "rateAverage": 4.5,
    "categoryId": "6278e4e919a7ab61193236f7",
    "atributeId": "",
    "descriptions": "Canon EOS 4000D DSLR Camera with EF-S 18-55mm f/3.5-5.6 III Lens & 500mm Preset Lens Beginner’s Bundle - Includes: SanDisk..."
  },
  {
    "sku": "B071R6JRZZ",
    "title": "Panasonic LUMIX DC-ZS70K, 20.3 Megapixel, 4K Digital Camera, Touch Enabled 3-Inch 180 Degree Flip-front Display, 30X LEICA...",
    "metaTitle": "Panasonic LUMIX DC-ZS70K, 20.3 Megapixel, 4K Digital Camera, Touch Enabled 3-Inch 180 Degree Flip-front Display, 30X LEICA...",
    "imageUrls": "https://m.media-amazon.com/images/I/91LeogPYpHL._AC_UY218_.jpg",
    "status": "new",
    "price": 397.99,
    "discount": 6,
    "quantity": 111,
    "totalRatings": 1222,
    "rateAverage": 4.3,
    "categoryId": "6278e4e919a7ab61193236f7",
    "atributeId": "",
    "descriptions": "Panasonic LUMIX DC-ZS70K, 20.3 Megapixel, 4K Digital Camera, Touch Enabled 3-Inch 180 Degree Flip-front Display, 30X LEICA..."
  },
  {
    "sku": "B019UDI5PO",
    "title": "Canon PowerShot SX420 Digital Camera w/ 42x Optical Zoom - Wi-Fi & NFC Enabled (Black)",
    "metaTitle": "Canon PowerShot SX420 Digital Camera w/ 42x Optical Zoom - Wi-Fi & NFC Enabled (Black)",
    "imageUrls": "https://m.media-amazon.com/images/I/41a0leiV5DL._AC_UY218_.jpg",
    "status": "sale",
    "price": 237,
    "discount": 9,
    "quantity": 77,
    "totalRatings": 2581,
    "rateAverage": 4.3,
    "categoryId": "6278e4e919a7ab61193236f7",
    "atributeId": "",
    "descriptions": "Canon PowerShot SX420 Digital Camera w/ 42x Optical Zoom - Wi-Fi & NFC Enabled (Black)"
  },
  {
    "sku": "B0007UQNKY",
    "title": "Sponsored Ad - Celestron - PowerSeeker 127EQ Telescope - Manual German Equatorial Telescope for Beginners - Compact and Po...",
    "metaTitle": "Sponsored Ad - Celestron - PowerSeeker 127EQ Telescope - Manual German Equatorial Telescope for Beginners - Compact and Po...",
    "imageUrls": "https://m.media-amazon.com/images/I/61Squ7U2zRL._AC_UY218_.jpg",
    "status": "sale",
    "price": 179.95,
    "discount": 11,
    "quantity": 84,
    "totalRatings": 6856,
    "rateAverage": 4.2,
    "categoryId": "6278e4e919a7ab61193236f7",
    "atributeId": "",
    "descriptions": "Sponsored Ad - Celestron - PowerSeeker 127EQ Telescope - Manual German Equatorial Telescope for Beginners - Compact and Po..."
  },
  {
    "sku": "B07MC572D3",
    "title": "Sponsored Ad - SME WiFi Spotting Scope Camera",
    "metaTitle": "Sponsored Ad - SME WiFi Spotting Scope Camera",
    "imageUrls": "https://m.media-amazon.com/images/I/515YqPGPV3L._AC_UY218_.jpg",
    "status": "new",
    "price": 81.43,
    "discount": 11,
    "quantity": 88,
    "totalRatings": 371,
    "rateAverage": 3.9,
    "categoryId": "6278e4e919a7ab61193236f7",
    "atributeId": "",
    "descriptions": "Sponsored Ad - SME WiFi Spotting Scope Camera"
  },
  {
    "sku": "B0101RW3QK",
    "title": "Canon EOS REBEL T7 DSLR Camera|2 Lens Kit with EF18-55mm + EF 75-300mm Lens, Black",
    "metaTitle": "Canon EOS REBEL T7 DSLR Camera|2 Lens Kit with EF18-55mm + EF 75-300mm Lens, Black",
    "imageUrls": "https://m.media-amazon.com/images/I/71W1KvLH3sL._AC_UY218_.jpg",
    "status": "new",
    "price": 148,
    "discount": 5,
    "quantity": 82,
    "totalRatings": 1113,
    "rateAverage": 4.8,
    "categoryId": "6278e4e919a7ab61193236f7",
    "atributeId": "",
    "descriptions": "Canon EOS REBEL T7 DSLR Camera|2 Lens Kit with EF18-55mm + EF 75-300mm Lens, Black"
  },
  {
    "sku": "B00THKEKEQ",
    "title": "Nikon Coolpix L340 20.2 MP Digital Camera with 28x Optical Zoom and 3.0-Inch LCD (Black)",
    "metaTitle": "Nikon Coolpix L340 20.2 MP Digital Camera with 28x Optical Zoom and 3.0-Inch LCD (Black)",
    "imageUrls": "https://m.media-amazon.com/images/I/91zd5c1CzML._AC_UY218_.jpg",
    "status": "sale",
    "price": 479,
    "discount": 4,
    "quantity": 120,
    "totalRatings": 2195,
    "rateAverage": 4.3,
    "categoryId": "6278e4e919a7ab61193236f7",
    "atributeId": "",
    "descriptions": "Nikon Coolpix L340 20.2 MP Digital Camera with 28x Optical Zoom and 3.0-Inch LCD (Black)"
  },
  {
    "sku": "B003ZYF3LO",
    "title": "Nikon D3100 DSLR Camera with 18-55mm f/3.5-5.6 Auto Focus-S Nikkor Zoom Lens (Discontinued by Manufacturer)",
    "metaTitle": "Nikon D3100 DSLR Camera with 18-55mm f/3.5-5.6 Auto Focus-S Nikkor Zoom Lens (Discontinued by Manufacturer)",
    "imageUrls": "https://m.media-amazon.com/images/I/713u2gDQqML._AC_UY218_.jpg",
    "status": "new",
    "price": 200,
    "discount": 11,
    "quantity": 64,
    "totalRatings": 1415,
    "rateAverage": 4.6,
    "categoryId": "6278e4e919a7ab61193236f7",
    "atributeId": "",
    "descriptions": "Nikon D3100 DSLR Camera with 18-55mm f/3.5-5.6 Auto Focus-S Nikkor Zoom Lens (Discontinued by Manufacturer)"
  },
  {
    "sku": "B07P3FQ21B",
    "title": "Coolpix B600 Black",
    "metaTitle": "Coolpix B600 Black",
    "imageUrls": "https://m.media-amazon.com/images/I/81GdfR5WV0L._AC_UY218_.jpg",
    "status": "new",
    "price": 150,
    "discount": 9,
    "quantity": 81,
    "totalRatings": 147,
    "rateAverage": 4.4,
    "categoryId": "6278e4e919a7ab61193236f7",
    "atributeId": "",
    "descriptions": "Coolpix B600 Black"
  },
  {
    "sku": "B07HH1PVRZ",
    "title": "Canon Powershot SX70 20.3MP Digital Camera 65x Optical Zoom Lens 4K Video 3-inch LCD Tilt Screen (Black)",
    "metaTitle": "Canon Powershot SX70 20.3MP Digital Camera 65x Optical Zoom Lens 4K Video 3-inch LCD Tilt Screen (Black)",
    "imageUrls": "https://m.media-amazon.com/images/I/61HitByfSJL._AC_UY218_.jpg",
    "status": "sale",
    "price": 111,
    "discount": 9,
    "quantity": 43,
    "totalRatings": 318,
    "rateAverage": 4.3,
    "categoryId": "6278e4e919a7ab61193236f7",
    "atributeId": "",
    "descriptions": "Canon Powershot SX70 20.3MP Digital Camera 65x Optical Zoom Lens 4K Video 3-inch LCD Tilt Screen (Black)"
  },
  {
    "sku": "B0195XJAZI",
    "title": "Kodak PIXPRO Friendly Zoom FZ43-RD 16MP Digital Camera with 4X Optical Zoom and 2.7\" LCD Screen (Red)",
    "metaTitle": "Kodak PIXPRO Friendly Zoom FZ43-RD 16MP Digital Camera with 4X Optical Zoom and 2.7\" LCD Screen (Red)",
    "imageUrls": "https://m.media-amazon.com/images/I/81nYUsr44iL._AC_UY218_.jpg",
    "status": "new",
    "price": 397,
    "discount": 3,
    "quantity": 34,
    "totalRatings": 2543,
    "rateAverage": 4.2,
    "categoryId": "6278e4e919a7ab61193236f7",
    "atributeId": "",
    "descriptions": "Kodak PIXPRO Friendly Zoom FZ43-RD 16MP Digital Camera with 4X Optical Zoom and 2.7\" LCD Screen (Red)"
  },
  {
    "sku": "B09MC4XLB7",
    "title": "Canon EOS 4000D Rebel T100 DSLR Camera with EF S 18 55mm f/3.5 5.6 III CN4000DW1855IIIFB9VRM Canon EOS 4000D DSLR with EF ...",
    "metaTitle": "Canon EOS 4000D Rebel T100 DSLR Camera with EF S 18 55mm f/3.5 5.6 III CN4000DW1855IIIFB9VRM Canon EOS 4000D DSLR with EF ...",
    "imageUrls": "https://m.media-amazon.com/images/I/81pt1WAeLeL._AC_UY218_.jpg",
    "status": "new",
    "price": 469.95,
    "discount": 3,
    "quantity": 89,
    "totalRatings": 2,
    "rateAverage": 3,
    "categoryId": "6278e4e919a7ab61193236f7",
    "atributeId": "",
    "descriptions": "Canon EOS 4000D Rebel T100 DSLR Camera with EF S 18 55mm f/3.5 5.6 III CN4000DW1855IIIFB9VRM Canon EOS 4000D DSLR with EF ..."
  },
  {
    "sku": "B081ZXPJL1",
    "title": "Sponsored Ad - UBeesize 10’’ LED Ring Light with Stand and Phone Holder, Selfie Halo Light for Photography/Makeup/Vloggin...",
    "metaTitle": "Sponsored Ad - UBeesize 10’’ LED Ring Light with Stand and Phone Holder, Selfie Halo Light for Photography/Makeup/Vloggin...",
    "imageUrls": "https://m.media-amazon.com/images/I/61x7Mlnf3xL._AC_UY218_.jpg",
    "status": "new",
    "price": 35.99,
    "discount": 11,
    "quantity": 31,
    "totalRatings": 14290,
    "rateAverage": 4.5,
    "categoryId": "6278e4e919a7ab61193236f7",
    "atributeId": "",
    "descriptions": "Sponsored Ad - UBeesize 10’’ LED Ring Light with Stand and Phone Holder, Selfie Halo Light for Photography/Makeup/Vloggin..."
  },
  {
    "sku": "B07B45D8WV",
    "title": "Sony a7 III (ILCEM3K/B) Full-frame Mirrorless Interchangeable-Lens Camera with 28-70mm Lens with 3-Inch LCD, Black",
    "metaTitle": "Sony a7 III (ILCEM3K/B) Full-frame Mirrorless Interchangeable-Lens Camera with 28-70mm Lens with 3-Inch LCD, Black",
    "imageUrls": "https://m.media-amazon.com/images/I/91rQ3XfEYzL._AC_UY218_.jpg",
    "status": "new",
    "price": 459,
    "discount": 5,
    "quantity": 104,
    "totalRatings": 1777,
    "rateAverage": 4.7,
    "categoryId": "6278e4e919a7ab61193236f7",
    "atributeId": "",
    "descriptions": "Sony a7 III (ILCEM3K/B) Full-frame Mirrorless Interchangeable-Lens Camera with 28-70mm Lens with 3-Inch LCD, Black"
  },
  {
    "sku": "B07QK4SLQR",
    "title": "Godox V1C Camera Flash Speedlight Round Head Wireless 2.4G Compatible with Canon EOS Series 1500D 3000D 5D Mark ll/LLL/IV ...",
    "metaTitle": "Godox V1C Camera Flash Speedlight Round Head Wireless 2.4G Compatible with Canon EOS Series 1500D 3000D 5D Mark ll/LLL/IV ...",
    "imageUrls": "https://m.media-amazon.com/images/I/61CHXaC9ymL._AC_UY218_.jpg",
    "status": "sale",
    "price": 259,
    "discount": 11,
    "quantity": 32,
    "totalRatings": 30,
    "rateAverage": 4.8,
    "categoryId": "6278e4e919a7ab61193236f7",
    "atributeId": "",
    "descriptions": "Godox V1C Camera Flash Speedlight Round Head Wireless 2.4G Compatible with Canon EOS Series 1500D 3000D 5D Mark ll/LLL/IV ..."
  },
  {
    "sku": "B00908BMVE",
    "title": "Canon PowerShot SX500 IS 16.0 MP Digital Camera with 30x Wide-Angle Optical Image Stabilized Zoom and 3.0-Inch LCD (Black)...",
    "metaTitle": "Canon PowerShot SX500 IS 16.0 MP Digital Camera with 30x Wide-Angle Optical Image Stabilized Zoom and 3.0-Inch LCD (Black)...",
    "imageUrls": "https://m.media-amazon.com/images/I/31+74KsOzLL._AC_UY218_.jpg",
    "status": "sale",
    "price": 139,
    "discount": 8,
    "quantity": 39,
    "totalRatings": 704,
    "rateAverage": 4.5,
    "categoryId": "6278e4e919a7ab61193236f7",
    "atributeId": "",
    "descriptions": "Canon PowerShot SX500 IS 16.0 MP Digital Camera with 30x Wide-Angle Optical Image Stabilized Zoom and 3.0-Inch LCD (Black)..."
  },
  {
    "sku": "B07MFR9MDR",
    "title": "Sponsored Ad - SME Bullseye Long Range Camera",
    "metaTitle": "Sponsored Ad - SME Bullseye Long Range Camera",
    "imageUrls": "https://m.media-amazon.com/images/I/61bMbO8vKAL._AC_UY218_.jpg",
    "status": "new",
    "price": 496.85,
    "discount": 4,
    "quantity": 22,
    "totalRatings": 120,
    "rateAverage": 4.3,
    "categoryId": "6278e4e919a7ab61193236f7",
    "atributeId": "",
    "descriptions": "Sponsored Ad - SME Bullseye Long Range Camera"
  },
  {
    "sku": "B076ZRBQDP",
    "title": "Sponsored Ad - MegaGear Torres Mini Genuine Leather Camera Messenger Bag for Mirrorless, Instant and DSLR Cameras",
    "metaTitle": "Sponsored Ad - MegaGear Torres Mini Genuine Leather Camera Messenger Bag for Mirrorless, Instant and DSLR Cameras",
    "imageUrls": "https://m.media-amazon.com/images/I/71RawOXAd4L._AC_UY218_.jpg",
    "status": "sale",
    "price": 84.95,
    "discount": 7,
    "quantity": 65,
    "totalRatings": 244,
    "rateAverage": 4.8,
    "categoryId": "6278e4e919a7ab61193236f7",
    "atributeId": "",
    "descriptions": "Sponsored Ad - MegaGear Torres Mini Genuine Leather Camera Messenger Bag for Mirrorless, Instant and DSLR Cameras"
  },
  {
    "sku": "B01N9MCH0E",
    "title": "Canon PowerShot G9 X Mark II Compact Digital Camera w/ 1 Inch Sensor and 3inch LCD - Wi-Fi, NFC, & Bluetooth Enabled (Silver)",
    "metaTitle": "Canon PowerShot G9 X Mark II Compact Digital Camera w/ 1 Inch Sensor and 3inch LCD - Wi-Fi, NFC, & Bluetooth Enabled (Silver)",
    "imageUrls": "https://m.media-amazon.com/images/I/815ZjcZ35KL._AC_UY218_.jpg",
    "status": "new",
    "price": 139,
    "discount": 6,
    "quantity": 60,
    "totalRatings": 492,
    "rateAverage": 4.5,
    "categoryId": "6278e4e919a7ab61193236f7",
    "atributeId": "",
    "descriptions": "Canon PowerShot G9 X Mark II Compact Digital Camera w/ 1 Inch Sensor and 3inch LCD - Wi-Fi, NFC, & Bluetooth Enabled (Silver)"
  },
  {
    "sku": "B00W3SCHNU",
    "title": "Nikon 35mm f/1.8G AF-S DX Lens for Nikon DSLR Cameras (Renewed)",
    "metaTitle": "Nikon 35mm f/1.8G AF-S DX Lens for Nikon DSLR Cameras (Renewed)",
    "imageUrls": "https://m.media-amazon.com/images/I/71ol6QhGmTL._AC_UY218_.jpg",
    "status": "new",
    "price": 229.95,
    "discount": 2,
    "quantity": 82,
    "totalRatings": 301,
    "rateAverage": 4.8,
    "categoryId": "6278e4e919a7ab61193236f7",
    "atributeId": "",
    "descriptions": "Nikon 35mm f/1.8G AF-S DX Lens for Nikon DSLR Cameras (Renewed)"
  },
  {
    "sku": "B07KVLXT2M",
    "title": "Canon PowerShot SX740 Digital Camera w/40x Optical Zoom & 3 Inch Tilt LCD - 4K VIdeo, Wi-Fi, NFC, Bluetooth Enabled (Blac...",
    "metaTitle": "Canon PowerShot SX740 Digital Camera w/40x Optical Zoom & 3 Inch Tilt LCD - 4K VIdeo, Wi-Fi, NFC, Bluetooth Enabled (Blac...",
    "imageUrls": "https://m.media-amazon.com/images/I/71aIfDnMbdL._AC_UY218_.jpg",
    "status": "new",
    "price": 491.46,
    "discount": 5,
    "quantity": 56,
    "totalRatings": 66,
    "rateAverage": 4.2,
    "categoryId": "6278e4e919a7ab61193236f7",
    "atributeId": "",
    "descriptions": "Canon PowerShot SX740 Digital Camera w/40x Optical Zoom & 3 Inch Tilt LCD - 4K VIdeo, Wi-Fi, NFC, Bluetooth Enabled (Blac..."
  },
  {
    "sku": "B08C6CWVNZ",
    "title": "Canon EOS R5 Full-Frame Mirrorless Camera w/ RF24-105mm F4 L is USM Lens Kit - 8K Video, 45 Megapixel Full-Frame CMOS Sens...",
    "metaTitle": "Canon EOS R5 Full-Frame Mirrorless Camera w/ RF24-105mm F4 L is USM Lens Kit - 8K Video, 45 Megapixel Full-Frame CMOS Sens...",
    "imageUrls": "https://m.media-amazon.com/images/I/81depb5FkhL._AC_UY218_.jpg",
    "status": "new",
    "price": 319,
    "discount": 9,
    "quantity": 100,
    "totalRatings": 522,
    "rateAverage": 4.8,
    "categoryId": "6278e4e919a7ab61193236f7",
    "atributeId": "",
    "descriptions": "Canon EOS R5 Full-Frame Mirrorless Camera w/ RF24-105mm F4 L is USM Lens Kit - 8K Video, 45 Megapixel Full-Frame CMOS Sens..."
  },
  {
    "sku": "B086TTTZR5",
    "title": "Canon EOS RP Full-frame Mirrorless Interchangeable Lens Camera + RF24-105mm Lens F4-7.1 IS STM Lens Kit-- Compact and Ligh...",
    "metaTitle": "Canon EOS RP Full-frame Mirrorless Interchangeable Lens Camera + RF24-105mm Lens F4-7.1 IS STM Lens Kit-- Compact and Ligh...",
    "imageUrls": "https://m.media-amazon.com/images/I/811+58GXGOL._AC_UY218_.jpg",
    "status": "sale",
    "price": 479,
    "discount": 5,
    "quantity": 109,
    "totalRatings": 891,
    "rateAverage": 4.7,
    "categoryId": "6278e4e919a7ab61193236f7",
    "atributeId": "",
    "descriptions": "Canon EOS RP Full-frame Mirrorless Interchangeable Lens Camera + RF24-105mm Lens F4-7.1 IS STM Lens Kit-- Compact and Ligh..."
  },
  {
    "sku": "B0896TH11Y",
    "title": "Canon EOS 2000D (Rebel T7) DSLR Camera with EF-S 18-55mm f/3.5-5.6 DC III Lens & Deluxe Accessory Bundle – Includes: 2x Sa...",
    "metaTitle": "Canon EOS 2000D (Rebel T7) DSLR Camera with EF-S 18-55mm f/3.5-5.6 DC III Lens & Deluxe Accessory Bundle – Includes: 2x Sa...",
    "imageUrls": "https://m.media-amazon.com/images/I/81UIsDh3ysL._AC_UY218_.jpg",
    "status": "sale",
    "price": 529.95,
    "discount": 4,
    "quantity": 23,
    "totalRatings": 22,
    "rateAverage": 3.8,
    "categoryId": "6278e4e919a7ab61193236f7",
    "atributeId": "",
    "descriptions": "Canon EOS 2000D (Rebel T7) DSLR Camera with EF-S 18-55mm f/3.5-5.6 DC III Lens & Deluxe Accessory Bundle – Includes: 2x Sa..."
  },
  {
    "sku": "B08L5ZGKCZ",
    "title": "Nikon Z 6II FX-Format Mirrorless Camera Body w/NIKKOR Z 24-70mm f/4 S, Black",
    "metaTitle": "Nikon Z 6II FX-Format Mirrorless Camera Body w/NIKKOR Z 24-70mm f/4 S, Black",
    "imageUrls": "https://m.media-amazon.com/images/I/91rYykQZ7yL._AC_UY218_.jpg",
    "status": "new",
    "price": 2596.95,
    "discount": 7,
    "quantity": 25,
    "totalRatings": 282,
    "rateAverage": 4.8,
    "categoryId": "6278e4e919a7ab61193236f7",
    "atributeId": "",
    "descriptions": "Nikon Z 6II FX-Format Mirrorless Camera Body w/NIKKOR Z 24-70mm f/4 S, Black"
  },
  {
    "sku": "B088MMTS9P",
    "title": "Canon EOS R RF24-105mm F4-7.1 IS STM Lens Kit, Vlogging and Content Creator Camera 4K UHD, Digital Single-Lens Non-Reflex ...",
    "metaTitle": "Canon EOS R RF24-105mm F4-7.1 IS STM Lens Kit, Vlogging and Content Creator Camera 4K UHD, Digital Single-Lens Non-Reflex ...",
    "imageUrls": "https://m.media-amazon.com/images/I/71N++WQnA7L._AC_UY218_.jpg",
    "status": "new",
    "price": 371,
    "discount": 9,
    "quantity": 64,
    "totalRatings": 252,
    "rateAverage": 4.6,
    "categoryId": "6278e4e919a7ab61193236f7",
    "atributeId": "",
    "descriptions": "Canon EOS R RF24-105mm F4-7.1 IS STM Lens Kit, Vlogging and Content Creator Camera 4K UHD, Digital Single-Lens Non-Reflex ..."
  },
  {
    "sku": "B00K7O2DJU",
    "title": "Sony RX100 III 20.1 MP Premium Compact Digital Camera w/1-inch Sensor and 24-70mm F1.8-2.8 ZEISS Zoom Lens (DSCRX100M3/B),...",
    "metaTitle": "Sony RX100 III 20.1 MP Premium Compact Digital Camera w/1-inch Sensor and 24-70mm F1.8-2.8 ZEISS Zoom Lens (DSCRX100M3/B),...",
    "imageUrls": "https://m.media-amazon.com/images/I/71lRWSHdDRL._AC_UY218_.jpg",
    "status": "new",
    "price": 748,
    "discount": 6,
    "quantity": 24,
    "totalRatings": 588,
    "rateAverage": 4.5,
    "categoryId": "6278e4e919a7ab61193236f7",
    "atributeId": "",
    "descriptions": "Sony RX100 III 20.1 MP Premium Compact Digital Camera w/1-inch Sensor and 24-70mm F1.8-2.8 ZEISS Zoom Lens (DSCRX100M3/B),..."
  },
  {
    "sku": "B07PZB47HN",
    "title": "Panasonic LUMIX G95 20.3 Megapixel Mirrorless Camera, 12-60mm F3.5-5.6 Micro Four Thirds Lens, 5-Axis Dual I.S. 2, 4K 24p ...",
    "metaTitle": "Panasonic LUMIX G95 20.3 Megapixel Mirrorless Camera, 12-60mm F3.5-5.6 Micro Four Thirds Lens, 5-Axis Dual I.S. 2, 4K 24p ...",
    "imageUrls": "https://m.media-amazon.com/images/I/71pWwFObbFL._AC_UY218_.jpg",
    "status": "new",
    "price": 697.99,
    "discount": 6,
    "quantity": 52,
    "totalRatings": 130,
    "rateAverage": 4.5,
    "categoryId": "6278e4e919a7ab61193236f7",
    "atributeId": "",
    "descriptions": "Panasonic LUMIX G95 20.3 Megapixel Mirrorless Camera, 12-60mm F3.5-5.6 Micro Four Thirds Lens, 5-Axis Dual I.S. 2, 4K 24p ..."
  },
  {
    "sku": "B00RKNND2W",
    "title": "Canon PowerShot SX530 Digital Camera w/ 50X Optical Zoom - Wi-Fi & NFC Enabled (Black)",
    "metaTitle": "Canon PowerShot SX530 Digital Camera w/ 50X Optical Zoom - Wi-Fi & NFC Enabled (Black)",
    "imageUrls": "https://m.media-amazon.com/images/I/61xeTmAQDNL._AC_UY218_.jpg",
    "status": "sale",
    "price": 169,
    "discount": 3,
    "quantity": 86,
    "totalRatings": 1788,
    "rateAverage": 4.5,
    "categoryId": "6278e4e919a7ab61193236f7",
    "atributeId": "",
    "descriptions": "Canon PowerShot SX530 Digital Camera w/ 50X Optical Zoom - Wi-Fi & NFC Enabled (Black)"
  },
  {
    "sku": "B098GZR4D5",
    "title": "Sponsored Ad - Minolta 48 MP Dual Screen Waterproof Digital Camera MN40WP",
    "metaTitle": "Sponsored Ad - Minolta 48 MP Dual Screen Waterproof Digital Camera MN40WP",
    "imageUrls": "https://m.media-amazon.com/images/I/71ezSbCylyS._AC_UY218_.jpg",
    "status": "new",
    "price": 101.99,
    "discount": 10,
    "quantity": 29,
    "totalRatings": 15,
    "rateAverage": 3.9,
    "categoryId": "6278e4e919a7ab61193236f7",
    "atributeId": "",
    "descriptions": "Sponsored Ad - Minolta 48 MP Dual Screen Waterproof Digital Camera MN40WP"
  },
  {
    "sku": "B07MFR9MDR",
    "title": "Sponsored Ad - SME Bullseye Long Range Camera",
    "metaTitle": "Sponsored Ad - SME Bullseye Long Range Camera",
    "imageUrls": "https://m.media-amazon.com/images/I/61bMbO8vKAL._AC_UY218_.jpg",
    "status": "sale",
    "price": 496.85,
    "discount": 7,
    "quantity": 96,
    "totalRatings": 120,
    "rateAverage": 4.3,
    "categoryId": "6278e4e919a7ab61193236f7",
    "atributeId": "",
    "descriptions": "Sponsored Ad - SME Bullseye Long Range Camera"
  },
  {
    "sku": "B07ZBNXFCM",
    "title": "Canon PowerShot ELPH 180 Digital Camera + 64 GB Memory Card (Red)",
    "metaTitle": "Canon PowerShot ELPH 180 Digital Camera + 64 GB Memory Card (Red)",
    "imageUrls": "https://m.media-amazon.com/images/I/71oXRnwKokL._AC_UY218_.jpg",
    "status": "new",
    "price": 399.95,
    "discount": 7,
    "quantity": 26,
    "totalRatings": 14,
    "rateAverage": 4.1,
    "categoryId": "6278e4e919a7ab61193236f7",
    "atributeId": "",
    "descriptions": "Canon PowerShot ELPH 180 Digital Camera + 64 GB Memory Card (Red)"
  },
  {
    "sku": "B01FFACPRA",
    "title": "Canon PowerShot SX620 Digital Camera w/25x Optical Zoom - Wi-Fi & NFC Enabled (Red)",
    "metaTitle": "Canon PowerShot SX620 Digital Camera w/25x Optical Zoom - Wi-Fi & NFC Enabled (Red)",
    "imageUrls": "https://m.media-amazon.com/images/I/711k3aLLqNL._AC_UY218_.jpg",
    "status": "new",
    "price": 269,
    "discount": 2,
    "quantity": 37,
    "totalRatings": 1352,
    "rateAverage": 4.4,
    "categoryId": "6278e4e919a7ab61193236f7",
    "atributeId": "",
    "descriptions": "Canon PowerShot SX620 Digital Camera w/25x Optical Zoom - Wi-Fi & NFC Enabled (Red)"
  },
  {
    "sku": "B00KOUIBZW",
    "title": "Panasonic LUMIX FZ1000 4K Point and Shoot Camera, 16X LEICA DC VARIO-ELMARIT F2.8-4.0 Lens, 21.1 Megapixels, 1 Inch High S...",
    "metaTitle": "Panasonic LUMIX FZ1000 4K Point and Shoot Camera, 16X LEICA DC VARIO-ELMARIT F2.8-4.0 Lens, 21.1 Megapixels, 1 Inch High S...",
    "imageUrls": "https://m.media-amazon.com/images/I/61cuHZTs8LL._AC_UY218_.jpg",
    "status": "sale",
    "price": 361,
    "discount": 9,
    "quantity": 29,
    "totalRatings": 709,
    "rateAverage": 4.5,
    "categoryId": "6278e4e919a7ab61193236f7",
    "atributeId": "",
    "descriptions": "Panasonic LUMIX FZ1000 4K Point and Shoot Camera, 16X LEICA DC VARIO-ELMARIT F2.8-4.0 Lens, 21.1 Megapixels, 1 Inch High S..."
  },
  {
    "sku": "B08PCCXCGS",
    "title": "Canon PowerShot SX620 HS Digital Camera (Black) with Advanced Accessory Bundle - Includes: SanDisk Ultra 64GB Memory Card,...",
    "metaTitle": "Canon PowerShot SX620 HS Digital Camera (Black) with Advanced Accessory Bundle - Includes: SanDisk Ultra 64GB Memory Card,...",
    "imageUrls": "https://m.media-amazon.com/images/I/51piA5bLIEL._AC_UY218_.jpg",
    "status": "sale",
    "price": 395,
    "discount": 11,
    "quantity": 29,
    "totalRatings": 13,
    "rateAverage": 4.5,
    "categoryId": "6278e4e919a7ab61193236f7",
    "atributeId": "",
    "descriptions": "Canon PowerShot SX620 HS Digital Camera (Black) with Advanced Accessory Bundle - Includes: SanDisk Ultra 64GB Memory Card,..."
  },
  {
    "sku": "B07QBD256Y",
    "title": "Canon EOS REBEL SL3 Digital SLR Camera with EF-S 18-55mm Lens kit, Built-in Wi-Fi, Dual Pixel CMOS AF and 3.0 Inch Vari-An...",
    "metaTitle": "Canon EOS REBEL SL3 Digital SLR Camera with EF-S 18-55mm Lens kit, Built-in Wi-Fi, Dual Pixel CMOS AF and 3.0 Inch Vari-An...",
    "imageUrls": "https://m.media-amazon.com/images/I/71-YNbmRcDL._AC_UY218_.jpg",
    "status": "sale",
    "price": 164,
    "discount": 6,
    "quantity": 29,
    "totalRatings": 1105,
    "rateAverage": 4.8,
    "categoryId": "6278e4e919a7ab61193236f7",
    "atributeId": "",
    "descriptions": "Canon EOS REBEL SL3 Digital SLR Camera with EF-S 18-55mm Lens kit, Built-in Wi-Fi, Dual Pixel CMOS AF and 3.0 Inch Vari-An..."
  },
  {
    "sku": "B019XLL4F6",
    "title": "Kodak PIXPRO Friendly Zoom FZ53-RD 16MP Digital Camera with 5X Optical Zoom and 2.7\" LCD Screen (Red)",
    "metaTitle": "Kodak PIXPRO Friendly Zoom FZ53-RD 16MP Digital Camera with 5X Optical Zoom and 2.7\" LCD Screen (Red)",
    "imageUrls": "https://m.media-amazon.com/images/I/816hh1wRmrL._AC_UY218_.jpg",
    "status": "sale",
    "price": 323,
    "discount": 7,
    "quantity": 57,
    "totalRatings": 3197,
    "rateAverage": 4.3,
    "categoryId": "6278e4e919a7ab61193236f7",
    "atributeId": "",
    "descriptions": "Kodak PIXPRO Friendly Zoom FZ53-RD 16MP Digital Camera with 5X Optical Zoom and 2.7\" LCD Screen (Red)"
  },
  {
    "sku": "B01MR2D0OG",
    "title": "Nikon D5600 DSLR with 18-55mm f/3.5-5.6G VR and 70-300mm f/4.5-6.3G ED",
    "metaTitle": "Nikon D5600 DSLR with 18-55mm f/3.5-5.6G VR and 70-300mm f/4.5-6.3G ED",
    "imageUrls": "https://m.media-amazon.com/images/I/71huW72qomL._AC_UY218_.jpg",
    "status": "new",
    "price": 1096.95,
    "discount": 8,
    "quantity": 89,
    "totalRatings": 599,
    "rateAverage": 4.8,
    "categoryId": "6278e4e919a7ab61193236f7",
    "atributeId": "",
    "descriptions": "Nikon D5600 DSLR with 18-55mm f/3.5-5.6G VR and 70-300mm f/4.5-6.3G ED"
  },
  {
    "sku": "B07MV3P7M8",
    "title": "Sony Alpha a6400 Mirrorless Camera: Compact APS-C Interchangeable Lens Digital Camera with Real-Time Eye Auto Focus, 4K Vi...",
    "metaTitle": "Sony Alpha a6400 Mirrorless Camera: Compact APS-C Interchangeable Lens Digital Camera with Real-Time Eye Auto Focus, 4K Vi...",
    "imageUrls": "https://m.media-amazon.com/images/I/81XeVWWyUUL._AC_UY218_.jpg",
    "status": "new",
    "price": 416,
    "discount": 5,
    "quantity": 85,
    "totalRatings": 1371,
    "rateAverage": 4.8,
    "categoryId": "6278e4e919a7ab61193236f7",
    "atributeId": "",
    "descriptions": "Sony Alpha a6400 Mirrorless Camera: Compact APS-C Interchangeable Lens Digital Camera with Real-Time Eye Auto Focus, 4K Vi..."
  },
  {
    "sku": "B0007UQNKY",
    "title": "Sponsored Ad - Celestron - PowerSeeker 127EQ Telescope - Manual German Equatorial Telescope for Beginners - Compact and Po...",
    "metaTitle": "Sponsored Ad - Celestron - PowerSeeker 127EQ Telescope - Manual German Equatorial Telescope for Beginners - Compact and Po...",
    "imageUrls": "https://m.media-amazon.com/images/I/61Squ7U2zRL._AC_UY218_.jpg",
    "status": "new",
    "price": 179.95,
    "discount": 11,
    "quantity": 76,
    "totalRatings": 6856,
    "rateAverage": 4.2,
    "categoryId": "6278e4e919a7ab61193236f7",
    "atributeId": "",
    "descriptions": "Sponsored Ad - Celestron - PowerSeeker 127EQ Telescope - Manual German Equatorial Telescope for Beginners - Compact and Po..."
  },
  {
    "sku": "B081ZXPJL1",
    "title": "Sponsored Ad - UBeesize 10’’ LED Ring Light with Stand and Phone Holder, Selfie Halo Light for Photography/Makeup/Vloggin...",
    "metaTitle": "Sponsored Ad - UBeesize 10’’ LED Ring Light with Stand and Phone Holder, Selfie Halo Light for Photography/Makeup/Vloggin...",
    "imageUrls": "https://m.media-amazon.com/images/I/61x7Mlnf3xL._AC_UY218_.jpg",
    "status": "new",
    "price": 35.99,
    "discount": 4,
    "quantity": 31,
    "totalRatings": 14290,
    "rateAverage": 4.5,
    "categoryId": "6278e4e919a7ab61193236f7",
    "atributeId": "",
    "descriptions": "Sponsored Ad - UBeesize 10’’ LED Ring Light with Stand and Phone Holder, Selfie Halo Light for Photography/Makeup/Vloggin..."
  }
]
